gaga_phsp/__init__.py
gaga_phsp/gaga.py
gaga_phsp/gaga_functions.py
gaga_phsp/gaga_helpers.py
gaga_phsp/gaga_helpers_pet.py
gaga_phsp/gaga_helpers_plot.py
gaga_phsp/gaga_helpers_spect.py
gaga_phsp/gaga_helpers_tests.py
gaga_phsp/gaga_model.py
gaga_phsp/spect_intevo_helpers.py
gaga_phsp/bin/__init__.py
gaga_phsp/bin/gaga_convert_pth_to_pt.py
gaga_phsp/bin/gaga_exit_pos_to_ideal_pos.py
gaga_phsp/bin/gaga_gauss_cond_test.py
gaga_phsp/bin/gaga_gauss_plot.py
gaga_phsp/bin/gaga_gauss_test.py
gaga_phsp/bin/gaga_generate.py
gaga_phsp/bin/gaga_ideal_pos_to_exit_pos.py
gaga_phsp/bin/gaga_info.py
gaga_phsp/bin/gaga_pairs_to_tlor.py
gaga_phsp/bin/gaga_pet_merge_pairs.py
gaga_phsp/bin/gaga_pet_to_pairs.py
gaga_phsp/bin/gaga_pet_to_pairs2.py
gaga_phsp/bin/gaga_pet_to_pairs_old.py
gaga_phsp/bin/gaga_plot.py
gaga_phsp/bin/gaga_test_tlor.py
gaga_phsp/bin/gaga_tests.py
gaga_phsp/bin/gaga_tlor_to_pairs.py
gaga_phsp/bin/gaga_train.py
gaga_phsp-0.7.6.dist-info/licenses/LICENSE
tests/shape.py
tests/test001_non_cond.py
tests/test002_cond.py
tests/test003_param.py
tests/test004_main1_ref.py
tests/test004_main2_garf.py
tests/test004_main3_gaga.py
tests/test004_main4_standalone_numpy.py
tests/test004_main5_standalone_torch.py
tests/test005_pairs.py
tests/test006_helpers.py
tests/test006_pos_enc.py
gaga_phsp-0.7.6.dist-info/METADATA
gaga_phsp-0.7.6.dist-info/WHEEL
gaga_phsp-0.7.6.dist-info/entry_points.txt
gaga_phsp-0.7.6.dist-info/top_level.txt
gaga_phsp-0.7.6.dist-info/RECORD
