Metadata-Version: 2.4
Name: gaga-phsp
Version: 0.7.6
Summary: Python tools for GATE GAN simulations
Author-email: David Sarrut <david.sarrut@creatis.insa-lyon.fr>
License:                                  Apache License
Classifier: Programming Language :: Python :: 3
Classifier: License :: OSI Approved :: Apache Software License
Classifier: Operating System :: OS Independent
Requires-Python: >=3.8
License-File: LICENSE
Requires-Dist: tqdm
Requires-Dist: colorama
Requires-Dist: click
Requires-Dist: scipy
Requires-Dist: garf>=2.10
Requires-Dist: matplotlib
Requires-Dist: gatetools
Requires-Dist: pathlib
Dynamic: license-file
